odoo/addons/project_timeline/README.rst
odoo/addons/project_timeline/__init__.py
odoo/addons/project_timeline/__manifest__.py
odoo/addons/project_timeline/demo/project_project_demo.xml
odoo/addons/project_timeline/demo/project_task_demo.xml
odoo/addons/project_timeline/i18n/ar.po
odoo/addons/project_timeline/i18n/ca.po
odoo/addons/project_timeline/i18n/de.po
odoo/addons/project_timeline/i18n/el.po
odoo/addons/project_timeline/i18n/es.po
odoo/addons/project_timeline/i18n/es_AR.po
odoo/addons/project_timeline/i18n/es_CR.po
odoo/addons/project_timeline/i18n/es_MX.po
odoo/addons/project_timeline/i18n/es_VE.po
odoo/addons/project_timeline/i18n/fi.po
odoo/addons/project_timeline/i18n/fr.po
odoo/addons/project_timeline/i18n/fr_FR.po
odoo/addons/project_timeline/i18n/gl.po
odoo/addons/project_timeline/i18n/he.po
odoo/addons/project_timeline/i18n/hr.po
odoo/addons/project_timeline/i18n/hr_HR.po
odoo/addons/project_timeline/i18n/hu.po
odoo/addons/project_timeline/i18n/it.po
odoo/addons/project_timeline/i18n/ja.po
odoo/addons/project_timeline/i18n/lt.po
odoo/addons/project_timeline/i18n/lv.po
odoo/addons/project_timeline/i18n/mk.po
odoo/addons/project_timeline/i18n/mn.po
odoo/addons/project_timeline/i18n/nl.po
odoo/addons/project_timeline/i18n/nl_NL.po
odoo/addons/project_timeline/i18n/pl.po
odoo/addons/project_timeline/i18n/project_timeline.pot
odoo/addons/project_timeline/i18n/pt.po
odoo/addons/project_timeline/i18n/pt_BR.po
odoo/addons/project_timeline/i18n/pt_PT.po
odoo/addons/project_timeline/i18n/ro.po
odoo/addons/project_timeline/i18n/sl.po
odoo/addons/project_timeline/i18n/sv.po
odoo/addons/project_timeline/i18n/tr.po
odoo/addons/project_timeline/i18n/uk.po
odoo/addons/project_timeline/i18n/zh_CN.po
odoo/addons/project_timeline/models/__init__.py
odoo/addons/project_timeline/models/project_task.py
odoo/addons/project_timeline/readme/CONTRIBUTORS.md
odoo/addons/project_timeline/readme/DESCRIPTION.md
odoo/addons/project_timeline/readme/USAGE.md
odoo_addon_project_timeline-18.0.1.0.0.2.dist-info/METADATA
odoo_addon_project_timeline-18.0.1.0.0.2.dist-info/WHEEL
odoo_addon_project_timeline-18.0.1.0.0.2.dist-info/top_level.txt
odoo_addon_project_timeline-18.0.1.0.0.2.dist-info/RECORD
