Metadata-Version: 2.1
Name: odoo-addon-project_timeline
Version: 18.0.1.0.0.2
Requires-Python: >=3.10
Requires-Dist: odoo-addon-web_timeline==18.0.*
Requires-Dist: odoo==18.0.*
Summary: Timeline view for projects
Home-page: https://github.com/OCA/project
License: AGPL-3
Author: Tecnativa, Onestein, Odoo Community Association (OCA)
Author-email: support@odoo-community.org
Classifier: Programming Language :: Python
Classifier: Framework :: Odoo
Classifier: Framework :: Odoo :: 18.0
Classifier: License :: OSI Approved :: GNU Affero General Public License v3
